{
    "COMMON_OK": "確定",
    "COMMON_CANCEL": "取消",
    "COMMON_YES": "是",
    "COMMON_NO": "否",
    "COMMON_COPY": "複製",
    "COMMON_COPIED": "已複製",
    "COMMON_LOADING": "載入中…",
    "COMMON_RETRY": "重試",
    "COMMON_CLOSE": "關閉",

    "LOADING_VERSION": "正在檢查版本…",
    "LOADING_SIGNING_IN": "正在登入…",
    "LOADING_READY": "即將就緒…",

    "OUTDATED_TITLE": "Loader 已過時",
    "OUTDATED_BODY": "您的 Loader 版本與遠端版本不符。請下載最新版本以繼續。",
    "OUTDATED_CURRENT_VERSION": "目前版本",
    "OUTDATED_DOWNLOAD": "下載最新版本",
    "OUTDATED_RECHECK": "重新檢查",

    "UPDATING_TITLE": "正在更新 Loader",
    "UPDATING_BODY": "有新版本可用。正在自動下載並安裝。",
    "UPDATING_STARTING": "準備中…",
    "UPDATING_DOWNLOADING": "下載中",
    "UPDATING_VERIFYING": "驗證中…",
    "UPDATING_RESTARTING": "重新啟動中…",
    "UPDATING_ERROR": "更新失敗",
    "UPDATING_ERROR_GENERIC": "更新過程中出現錯誤。",
    "UPDATING_ERROR_FALLBACK": "回退到手動下載…",

    "LOGIN_WELCOME": "歡迎回來",
    "LOGIN_SUB": "登入以啟動您的 loader。",
    "LOGIN_EMAIL_LABEL": "電子郵件",
    "LOGIN_EMAIL_PLACEHOLDER": "您的電子郵件",
    "LOGIN_PASSWORD_LABEL": "密碼",
    "LOGIN_PASSWORD_PLACEHOLDER": "••••••••",
    "LOGIN_SHOW_PASSWORD": "顯示密碼",
    "LOGIN_HIDE_PASSWORD": "隱藏密碼",
    "LOGIN_REMEMBER_ME": "記住我",
    "LOGIN_DISCORD_RPC": "Discord 活動狀態",
    "LOGIN_SIGN_IN": "登入",
    "LOGIN_AUTHENTICATING": "正在驗證…",
    "LOGIN_FORGOT": "忘記密碼？",
    "LOGIN_REGISTER": "註冊帳戶 →",
    "LOGIN_EMPTY_FIELDS": "電子郵件和密碼均為必填項",

    "GAMES_WELCOME": "歡迎，{name}",
    "GAMES_BETA_PILL": "測試版",
    "GAMES_SELECT_TITLE": "選擇遊戲",
    "GAMES_SELECT_ARIA": "選擇遊戲",
    "GAMES_NO_GAMES": "沒有可用的遊戲。請聯絡客服。",
    "GAMES_SELECTED": "已選擇",
    "GAMES_VERSION": "版本",
    "GAMES_STATUS": "狀態",
    "GAMES_DOCS_BTN": "文件",
    "GAMES_LAUNCH": "啟動 {name}",
    "GAMES_LAUNCHING": "正在啟動 · {percent}%",
    "GAMES_INJECT_AGAIN": "重新注入",
    "GAMES_ATTACHED_BTN": "已附加",
    "GAMES_ATTACHED_MODAL_TITLE": "Loader 已附加",
    "GAMES_ATTACHED_MODAL_BODY": "在遊戲中按 {key} 開啟選單。",
    "GAMES_BE_OFF_TOAST": "BattlEye 已關閉 — 現在可以啟動了。",
    "GAMES_INJECT_DEFAULT_OK": "Loader 已附加",
    "GAMES_INJECT_DEFAULT_FAIL": "注入失敗",
    "GAMES_ENHANCED_HINT_TITLE": "使用說明",
    "GAMES_ENHANCED_HINT_STEP1": "請確認 GTA V 已關閉。",
    "GAMES_ENHANCED_HINT_STEP2": "點擊下方的啟動按鈕，然後透過你的啟動器（Rockstar / Steam / Epic）啟動 GTA V。",
    "GAMES_ENHANCED_HINT_NOTE": "Loader 最多等待 90 秒，遊戲完成初始化後會安全注入。",

    "USERINFO_TITLE": "使用者資訊",
    "USERINFO_REQUIRES_LOGIN": "請登入以查看使用者資訊。",
    "USERINFO_ID": "ID",
    "USERINFO_BETA": "測試使用者",
    "USERINFO_EMAIL_VERIFIED": "電子郵件已驗證",
    "USERINFO_CREATED": "建立於",
    "USERINFO_HWID_RESET": "HWID 重設於",
    "USERINFO_UPDATED": "更新於",
    "USERINFO_HW_TITLE": "硬體資訊",
    "USERINFO_HW_LABEL": "SHA-256",
    "USERINFO_REQUEST_RESET": "申請重設 HWID",
    "USERINFO_REQUEST_RESET_INFO": "請透過網站申請 HWID 重設。",

    "TITLEBAR_PROFILE": "個人資料",
    "TITLEBAR_LOGOUT": "登出",
    "TITLEBAR_BACK": "← 返回",
    "TITLEBAR_MINIMIZE": "最小化",
    "TITLEBAR_CLOSE": "關閉",
    "TITLEBAR_SETTINGS": "設定",
    "TITLEBAR_SHOW_IDENTITY": "顯示身分",
    "TITLEBAR_HIDE_IDENTITY": "隱藏身分",
    "TITLEBAR_LANGUAGE": "語言",

    "SETTINGS_TITLE": "設定",
    "SETTINGS_LANGUAGE": "語言",
    "SETTINGS_LANGUAGE_HELP": "用於 loader 介面。遊戲選單有其自己的語言設定。",
    "SETTINGS_DISCORD": "Discord 活動狀態",
    "SETTINGS_DISCORD_HELP": "在 Discord 上顯示您目前的活動。",
    "SETTINGS_REFRESH_TRANSLATIONS": "重新整理翻譯",
    "SETTINGS_REFRESH_HELP": "從 GitHub 重新下載最新翻譯。",

    "ERROR_INVALID_CREDS": "憑證無效",
    "ERROR_LOGIN_FAILED": "登入失敗",
    "ERROR_NO_SAVED_CREDS": "沒有已儲存的憑證",
    "ERROR_BATTLEYE_RUNNING": "注入前請先關閉 BattlEye",
    "ERROR_GAME_NOT_RUNNING": "遊戲未執行",
    "ERROR_DLL_DOWNLOAD_FAILED": "無法下載 DLL",
    "ERROR_INJECT_FAILED": "注入失敗",
    "ERROR_INJECT_NATIVE_EXCEPTION": "注入期間發生原生例外（請查看日誌）",
    "ERROR_INJECT_UNKNOWN_EXCEPTION": "注入期間發生未知 C++ 例外",
    "ERROR_HWID_RESET_FAILED": "HWID 重設失敗",
    "ERROR_VERSION_OUTDATED": "Loader 已過時",
    "ERROR_NO_SERVICE": "服務不可用",
    "ERROR_COPY_FAILED": "複製失敗",
    "ERROR_BRIDGE_UNAVAILABLE": "WebView2 橋接不可用（在 Loader 之外執行？）",
    "ERROR_NO_ACTIVE_PLAN": "您的帳號未綁定任何方案。請查看您的面板。",
    "ERROR_HWID_MISMATCH": "硬體 ID 與您帳號上的不符。請在面板中重設 HWID 後再登入。",
    "ERROR_USER_BANNED": "您的帳號已被封鎖。請聯絡客服。",
    "ERROR_USER_DELETED": "此帳號已被刪除。",
    "ERROR_EMAIL_NOT_VERIFIED": "登入前請驗證您的電子郵件。請檢查收件匣與垃圾郵件。",

    "CHANGELOG_TITLE": "最新動態",
    "CHANGELOG_SUBTITLE": "Loader 與遊戲的更新歷史。",
    "CHANGELOG_EMPTY": "暫無內容。",
    "CHANGELOG_NEW_TOOLTIP": "自上次造訪後的新內容",
    "CHANGELOG_SEE_ALL": "查看全部 ({count}) →",
    "CHANGELOG_TYPE_UPDATE": "更新",
    "CHANGELOG_TYPE_FEATURE": "新功能",
    "CHANGELOG_TYPE_BUGFIX": "修正",
    "CHANGELOG_TYPE_RELEASE": "發行",

    "SHOPS_TITLE": "官方商店",
    "SHOPS_NAV": "商店",
    "SHOPS_FILTER_ALL": "全部",
    "SHOPS_EMPTY_FILTERED": "目前沒有商店提供 {hack}。",
    "SHOPS_EMPTY": "目前沒有可用的商店。",
    "SHOPS_SOLD": "已售",
    "SHOPS_LEGEND_INTRO": "各遊戲的庫存：",
    "SHOPS_LEGEND_WEEKLY": "= 週卡",
    "SHOPS_LEGEND_LIFETIME": "= 永久",
    "SHOPS_TOOLTIP_WEEKLY": "{hack} 週卡：可用 {count}",
    "SHOPS_TOOLTIP_LIFETIME": "{hack} 永久：可用 {count}",

    "UPSELL_TITLE": "目錄中可用的輔助",
    "UPSELL_SUBTITLE": "查看在哪裡購買",
    "UPSELL_SEE_HACK": "購買 {hack}",
    "UPSELL_SEE_ALL": "查看商店 ({count})",

    "BUY_NOW": "立即購買",
    "BUY_NOW_RENEW": "續訂",

    "LOGIN_AVAILABLE_FOR": "支援的遊戲"
}
